.gitignore
LICENSE
README.md
setup.py
django_url_framework/__init__.py
django_url_framework/apps.py
django_url_framework/controller.py
django_url_framework/exceptions.py
django_url_framework/flash.py
django_url_framework/helper.py
django_url_framework/lib.py
django_url_framework/renderers.py
django_url_framework/site.py
django_url_framework.egg-info/PKG-INFO
django_url_framework.egg-info/SOURCES.txt
django_url_framework.egg-info/dependency_links.txt
django_url_framework.egg-info/pbr.json
django_url_framework.egg-info/top_level.txt
django_url_framework/decorators/__init__.py
django_url_framework/decorators/action_options.py
django_url_framework/decorators/auth.py
django_url_framework/decorators/http_methods.py
django_url_framework/decorators/render.py
django_url_framework/templatetags/__init__.py
django_url_framework/templatetags/url_framework.py
tests/__init__.py
tests/duf_test_case.py
tests/test_controller_action_renderers.py
tests/test_get_actions.py
tests/test_name_generation.py
tests/test_renderer_decorators.py