Metadata-Version: 2.1
Name: django-url-framework
Version: 0.6.0
Summary: Automagically discover urls in a django application, similar to the Ruby on Rails Controller/Action/View implementation.
Home-page: https://github.com/zeraien/django-url-framework/
Author: Dimo Fedortchenko
Author-email: d@angelhill.net
License: MIT
Platform: UNKNOWN
Classifier: Development Status :: 4 - Beta
Classifier: Environment :: Web Environment
Classifier: Framework :: Django
Classifier: Intended Audience :: Developers
Classifier: License :: OSI Approved :: MIT License
Classifier: Operating System :: OS Independent
Classifier: Programming Language :: Python :: 3
Classifier: Topic :: Utilities
License-File: LICENSE
